pixiv_down/__init__.py
pixiv_down/commands.py
pixiv_down/crawler.py
pixiv_down/utils.py
pixiv_down-0.1.8.dist-info/licenses/LICENSE
pixiv_down-0.1.8.dist-info/METADATA
pixiv_down-0.1.8.dist-info/WHEEL
pixiv_down-0.1.8.dist-info/entry_points.txt
pixiv_down-0.1.8.dist-info/top_level.txt
pixiv_down-0.1.8.dist-info/RECORD
