Metadata-Version: 2.4
Name: pixiv-down
Version: 0.1.8
Summary: Pixiv illusts downloader.
Author-email: Seamile <lanhuermao@gmail.com>
Classifier: Programming Language :: Python :: 3
Classifier: Operating System :: POSIX
Classifier: Operating System :: MacOS :: MacOS X
Classifier: Topic :: Utilities
Requires-Python: >=3.11
License-File: LICENSE
Requires-Dist: PixivPy>=3.7.0
Requires-Dist: requests==2.32.5
Requires-Dist: zhconv-rs==0.4.0
Dynamic: license-file
